xodapi/__init__.py
xodapi/constants.py
xodapi/driver_tools.py
xodapi/parsers.py
xodapi-1.0.3.dist-info/LICENSE
xodapi-1.0.3.dist-info/METADATA
xodapi-1.0.3.dist-info/WHEEL
xodapi-1.0.3.dist-info/top_level.txt
xodapi-1.0.3.dist-info/RECORD
