Metadata-Version: 2.1
Name: xodapi
Version: 1.0.3
Summary: Simple Python Wrapper for scraping and accessing Xoda Data
Home-page: https://github.com/REVL-Training/XodaAPI
Author: Liew Cher Don
Author-email: liewcherdon@gmail.com
Classifier: Programming Language :: Python :: 3.9
Classifier: License :: OSI Approved :: MIT License
Classifier: Operating System :: OS Independent
License-File: LICENSE
